ssh_telegram_manager/__init__.py
ssh_telegram_manager/core.py
ssh_telegram_manager/locale/en/LC_MESSAGES/ssh_telegram_manager.mo
ssh_telegram_manager/locale/en.po
ssh_telegram_manager/locale/es/LC_MESSAGES/ssh_telegram_manager.mo
ssh_telegram_manager/locale/es.po
ssh_telegram_manager/locale/ssh_telegram_manager.pot
ssh_telegram_manager/poethepoet.py
ssh_telegram_manager-1.0.0.dist-info/LICENSE
ssh_telegram_manager-1.0.0.dist-info/METADATA
ssh_telegram_manager-1.0.0.dist-info/WHEEL
ssh_telegram_manager-1.0.0.dist-info/entry_points.txt
ssh_telegram_manager-1.0.0.dist-info/RECORD
