Metadata-Version: 2.1
Name: ssh-telegram-manager
Version: 1.0.0
Summary: Python app to launch sshd server from Telegram
License: GPL-3
Author: turulomio
Author-email: turulomio@yahoo.es
Requires-Python: >=3.8,<4.0
Classifier: License :: Other/Proprietary License
Classifier: Programming Language :: Python :: 3
Classifier: Programming Language :: Python :: 3.8
Classifier: Programming Language :: Python :: 3.9
Classifier: Programming Language :: Python :: 3.10
Classifier: Programming Language :: Python :: 3.11
Classifier: Programming Language :: Python :: 3.12
Requires-Dist: python-telegram-bot (>=21.4)
